.gitignore
LICENSE.txt
MANIFEST.in
README.md
__init__.py
setup.py
distributors/__init__.py
distributors/cache.py
distributors/clean.py
distributors/coffeescript.py
distributors/dist.py
distributors/downloads.py
distributors/settings.py
distributors/xwhich.py
distributors/urlobject/__init__.py
distributors/urlobject/netloc.py
distributors/urlobject/path.py
distributors/urlobject/ports.py
distributors/urlobject/query_string.py
distributors/urlobject/urlobject.py
django_signalqueue.egg-info/PKG-INFO
django_signalqueue.egg-info/SOURCES.txt
django_signalqueue.egg-info/dependency_links.txt
django_signalqueue.egg-info/entry_points.txt
django_signalqueue.egg-info/requires.txt
django_signalqueue.egg-info/top_level.txt
signalqueue/__init__.py
signalqueue/admin.py
signalqueue/dispatcher.py
signalqueue/mappings.py
signalqueue/models.py
signalqueue/signals.py
signalqueue/testrunner.py
signalqueue/tests.py
signalqueue/utils.py
signalqueue/fixtures/TESTMODEL-DUMP.json
signalqueue/fixtures/TESTMODEL-ENQUEUED-SIGNALS.json
signalqueue/management/__init__.py
signalqueue/management/commands/__init__.py
signalqueue/management/commands/dequeue.py
signalqueue/management/commands/dumpqueue.py
signalqueue/management/commands/runqueueserver.py
signalqueue/settings/__init__.py
signalqueue/settings/redis-compatible.conf
signalqueue/settings/redis.conf
signalqueue/settings/test_async.py
signalqueue/settings/test_sync.py
signalqueue/settings/urlconf.py
signalqueue/static/signalqueue/coffee/jquery.signalqueue.coffee
signalqueue/static/signalqueue/js/jquery.queuestatus.js
signalqueue/static/signalqueue/js/jquery.signalqueue.js
signalqueue/static/socket.io-client/WebSocketMain.swf
signalqueue/static/socket.io-client/WebSocketMainInsecure.swf
signalqueue/static/socket.io-client/flashpolicy.xml
signalqueue/static/socket.io-client/socket.io.js
signalqueue/static/socket.io-client/socket.io.min.js
signalqueue/templates/status.html
signalqueue/templates/admin/app_index.html
signalqueue/templates/admin/index_with_queues.html
signalqueue/templates/admin/sidebar_queue_module.html
signalqueue/templatetags/__init__.py
signalqueue/templatetags/signalqueue_status.py
signalqueue/worker/__init__.py
signalqueue/worker/backends.py
signalqueue/worker/base.py
